medapy/__init__.py
medapy/ms_array.py
medapy/ms_pandas.py
medapy/ms_pint_formatter.py
medapy/analysis/__init__.py
medapy/analysis/proc_pandas.py
medapy/analysis/electron_transport/__init__.py
medapy/analysis/electron_transport/electron_transport.py
medapy/analysis/electron_transport/etr_pandas.py
medapy/collection/__init__.py
medapy/collection/mcollection.py
medapy/collection/mfile.py
medapy/collection/parameter.py
medapy/collection/parameter_definitions.json
medapy/plot_config/__init__.py
medapy/plot_config/cmaps/__init__.py
medapy/plot_config/cmaps/_from_reference_colors.py
medapy/plot_config/cmaps/bmrog.py
medapy/plot_config/cmaps/ogb.py
medapy/plot_config/styles/__init__.py
medapy/plot_config/styles/publication.py
medapy/utils/__init__.py
medapy/utils/constants.py
medapy/utils/misc.py
medapy/utils/validations.py
medapy/utils/warnings.py
medapy-0.4.0a0.dist-info/licenses/LICENSE.txt
medapy-0.4.0a0.dist-info/METADATA
medapy-0.4.0a0.dist-info/WHEEL
medapy-0.4.0a0.dist-info/top_level.txt
medapy-0.4.0a0.dist-info/RECORD
