Metadata-Version: 2.4
Name: medapy
Version: 0.4.0a0
Summary: A Python package to work with measured data
Project-URL: Homepage, https://github.com/medapy/medapy
Requires-Python: >=3.10
License-File: LICENSE.txt
Requires-Dist: numpy>=2.2
Requires-Dist: pandas>=2.2
Requires-Dist: pint>=0.24
Requires-Dist: pint-pandas>=0.7
Provides-Extra: fit
Requires-Dist: scipy>=1.15; extra == "fit"
Requires-Dist: numdifftools>=0.9; extra == "fit"
Requires-Dist: lmfit>=1.3; extra == "fit"
Provides-Extra: plot
Requires-Dist: matplotlib>=3.10; extra == "plot"
Provides-Extra: test
Requires-Dist: pytest>=8.0; extra == "test"
Provides-Extra: all
Requires-Dist: medapy[fit,plot]; extra == "all"
Dynamic: license-file
